statesegmentation/__init__.py
statesegmentation/gsbs.py
statesegmentation-0.0.6.dist-info/LICENSE
statesegmentation-0.0.6.dist-info/METADATA
statesegmentation-0.0.6.dist-info/WHEEL
statesegmentation-0.0.6.dist-info/top_level.txt
statesegmentation-0.0.6.dist-info/RECORD
