Metadata-Version: 2.1
Name: statesegmentation
Version: 0.0.6
Summary: Detecting neural state transitions underlying event segmentation
Home-page: https://github.com/lgeerligs/statesegmentation
Author: Linda Geerligs, Umut Güçlü
License: MIT
License-File: LICENSE
